reddit_dl/__init__.py
reddit_dl/__main__.py
reddit_dl/constants.py
reddit_dl/downloader.py
reddit_dl/exceptions.py
reddit_dl/reddit_dl.py
reddit_dl/redgifs.py
reddit_dl/utils.py
reddit_dl-0.0.3.dist-info/LICENSE
reddit_dl-0.0.3.dist-info/METADATA
reddit_dl-0.0.3.dist-info/WHEEL
reddit_dl-0.0.3.dist-info/entry_points.txt
reddit_dl-0.0.3.dist-info/top_level.txt
reddit_dl-0.0.3.dist-info/RECORD
