Metadata-Version: 2.1
Name: reddit-dl
Version: 0.0.3
Summary: Limitless Reddit Downloader. No API no LIMIT.
Author-email: redloaders <redloader@tutanota.com>
Project-URL: Homepage, https://github.com/reddit-dl/reddit-dl
Project-URL: Bug Tracker, https://github.com/reddit-dl/reddit-dl/issues
Classifier: Programming Language :: Python :: 3
Classifier: License :: OSI Approved :: MIT License
Classifier: Operating System :: OS Independent
Requires-Python: >=3.7
License-File: LICENSE
Requires-Dist: beautifulsoup4 (>=4.12)
Requires-Dist: m3u8 (>=3.5)
Requires-Dist: requests (>=2.31)
